facet/__init__.py
facet/_types.py
facet/py.typed
facet/data/__init__.py
facet/data/_sample.py
facet/data/partition/__init__.py
facet/data/partition/_partition.py
facet/explanation/__init__.py
facet/explanation/_explanation.py
facet/explanation/_types.py
facet/explanation/base/__init__.py
facet/explanation/base/_base.py
facet/explanation/parallel/__init__.py
facet/explanation/parallel/_parallel.py
facet/inspection/__init__.py
facet/inspection/_explainer.py
facet/inspection/_function_inspector.py
facet/inspection/_inspection.py
facet/inspection/_learner_inspector.py
facet/inspection/_shap_context.py
facet/inspection/_shap_projection.py
facet/inspection/base/__init__.py
facet/inspection/base/_model_inspector.py
facet/inspection/shap/__init__.py
facet/inspection/shap/_function.py
facet/inspection/shap/_shap.py
facet/inspection/shap/sklearn/__init__.py
facet/inspection/shap/sklearn/_sklearn.py
facet/selection/__init__.py
facet/selection/_parameters.py
facet/selection/_selection.py
facet/selection/base/__init__.py
facet/selection/base/_parameters.py
facet/simulation/__init__.py
facet/simulation/_result.py
facet/simulation/_simulation.py
facet/simulation/base/__init__.py
facet/simulation/base/_base.py
facet/simulation/viz/__init__.py
facet/simulation/viz/_draw.py
facet/simulation/viz/_style.py
facet/validation/__init__.py
facet/validation/_validation.py
gamma_facet-2.2.2.dist-info/licenses/LICENSE
gamma_facet-2.2.2.dist-info/WHEEL
gamma_facet-2.2.2.dist-info/METADATA
gamma_facet-2.2.2.dist-info/RECORD
