Metadata-Version: 2.4
Name: gamma-facet
Version: 2.2.2
Summary: Human-explainable AI.
Home-page: https://github.com/BCG-X-Official/facet
Author: Boston Consulting Group (BCG)
Requires-Python: >=3.10,<4a
License: Apache Software License v2.0
Classifier: Development Status :: 5 - Production/Stable
Classifier: Intended Audience :: Science/Research
Classifier: License :: OSI Approved :: Apache Software License
Classifier: Operating System :: MacOS
Classifier: Operating System :: Microsoft :: Windows
Classifier: Operating System :: POSIX :: Linux
Classifier: Operating System :: Unix
Classifier: Programming Language :: Python
Classifier: Programming Language :: Python :: 3
Classifier: Programming Language :: Python :: 3.9
Classifier: Programming Language :: Python :: 3.10
Classifier: Programming Language :: Python :: 3.11
Classifier: Programming Language :: Python :: 3.12
Classifier: Topic :: Scientific/Engineering
License-File: LICENSE
Requires-Dist: gamma-pytools     ~=3.0
Requires-Dist: matplotlib        ~=3.6
Requires-Dist: numpy             >=1.23,<3a
Requires-Dist: packaging         >=20
Requires-Dist: pandas            >=1.5,<3a
Requires-Dist: scipy             ~=1.9
Requires-Dist: shap              ~=0.45
Requires-Dist: scikit-learn      ~=1.3
Requires-Dist: sklearndf         ~=2.4
Requires-Dist: typing_extensions ~=4.0
Requires-Dist: sphinx ~= 4.5 ; extra == "docs"
Requires-Dist: sphinx-autodoc-typehints ~= 1.19 ; extra == "docs"
Requires-Dist: pydata-sphinx-theme ~= 0.8.1 ; extra == "docs"
Requires-Dist: jinja2 ~= 2.11 ; extra == "docs"
Requires-Dist: nbsphinx ~= 0.8.9 ; extra == "docs"
Requires-Dist: jupyter == 1 ; extra == "docs"
Requires-Dist: docutils ~= 0.17 ; extra == "docs"
Requires-Dist: xlrd ~= 1.2 ; extra == "docs"
Requires-Dist: m2r ~= 0.2 ; extra == "docs"
Requires-Dist: pytest ~= 8.1 ; extra == "testing"
Requires-Dist: pytest-cov ~= 4.1 ; extra == "testing"
Requires-Dist: lightgbm ~= 4.6 ; extra == "testing"
Project-URL: Documentation, https://bcg-x-official.github.io/facet/
Project-URL: Repository, https://github.com/BCG-X-Official/facet
Provides-Extra: docs
Provides-Extra: testing
